telesnake/__init__.py
telesnake/bot.py
telesnake/cog.py
telesnake/context.py
telesnake/types/__init__.py
telesnake/types/callback.py
telesnake/types/chat.py
telesnake/types/message.py
telesnake/types/user.py
telesnake/utils/__init__.py
telesnake/utils/keyboard.py
Telesnake-0.2.dist-info/LICENSE.md
Telesnake-0.2.dist-info/METADATA
Telesnake-0.2.dist-info/WHEEL
Telesnake-0.2.dist-info/top_level.txt
Telesnake-0.2.dist-info/RECORD
