Metadata-Version: 2.1
Name: Telesnake
Version: 0.2
Summary: Telegram API wrapper
Home-page: https://github.com/art3m4ik3/telesnake
Author: art3m4ik3
Author-email: art3m4ik3@gmail.com
License: MIT
Project-URL: Website, https://ll-u.ru
Project-URL: Source code, https://github.com/art3m4ik3/telesnake
Project-URL: Issues, https://github.com/art3m4ik3/telesnake/issues
Classifier: Programming Language :: Python :: 3
Classifier: License :: OSI Approved :: MIT License
Classifier: Operating System :: OS Independent
Requires-Python: >=3.8
License-File: LICENSE.md
Requires-Dist: aiohttp
